aicoder/AICoder.py
aicoder/AICoderFull.py
aicoder/AICoderPartial.py
aicoder/AICoderPrompts.py
aicoder/__init__.py
aicoder/main.py
aicoder-0.4.4.dist-info/LICENSE
aicoder-0.4.4.dist-info/METADATA
aicoder-0.4.4.dist-info/WHEEL
aicoder-0.4.4.dist-info/entry_points.txt
aicoder-0.4.4.dist-info/top_level.txt
aicoder-0.4.4.dist-info/RECORD
